plsno429/__init__.py
plsno429/algorithms.py
plsno429/base.py
plsno429/decorators.py
plsno429/exceptions.py
plsno429/types.py
plsno429/utils.py
plsno429-0.2.2.dist-info/METADATA
plsno429-0.2.2.dist-info/WHEEL
plsno429-0.2.2.dist-info/entry_points.txt
plsno429-0.2.2.dist-info/licenses/LICENSE
plsno429-0.2.2.dist-info/RECORD
