Metadata-Version: 2.4
Name: plsno429
Version: 0.2.2
Summary: A tiny Python library that politely says pls no 429 by auto-handling OpenAI rate limits.
Project-URL: Homepage, https://github.com/appleparan/plsno429
Author-email: Jongsu Liam Kim <jongsukim8@gmail.com>
License-File: LICENSE
Keywords: 429-error,api-client,artificial-intelligence,async,backoff,http-client,openai,rate-limiting,retry,throttling
Classifier: Development Status :: 4 - Beta
Classifier: Intended Audience :: Developers
Classifier: License :: OSI Approved :: Apache Software License
Classifier: Operating System :: OS Independent
Classifier: Programming Language :: Python
Classifier: Programming Language :: Python :: 3.12
Classifier: Programming Language :: Python :: 3.13
Classifier: Topic :: Internet :: WWW/HTTP :: Dynamic Content
Classifier: Topic :: Internet :: WWW/HTTP :: HTTP Servers
Classifier: Topic :: Scientific/Engineering :: Artificial Intelligence
Classifier: Topic :: Software Development :: Libraries :: Python Modules
Classifier: Topic :: System :: Networking
Classifier: Typing :: Typed
Requires-Python: <4.0,>=3.12
